{
    "version":  "1.0.63",
    "channel":  "stable",
    "zipUrl":  "https://shalestorage.z13.web.core.windows.net/ShaleApp-1.0.63.zip",
    "installerUrl":  "https://shalestorage.z13.web.core.windows.net/Shale-1.0.63.exe",
    "notes":  "Release 1.0.63",
    "mandatory":  false,
    "sha256":  "5f8539a90b9c7f4d63d71500d2db073691a62faf4c88a297e344561241317f7f",
    "publishedAt":  "2026-03-31T16:56:09Z",
    "macZipUrl":  "https://shalestorage.z13.web.core.windows.net/ShaleApp-1.0.63-mac.zip",
    "macSha256":  "85ad26c0cf07a1db2eba0561fdcf2bcefe968f4985ec094724c4f4d9ff25d121"
}
